[
  {
    "page": "/",
    "timestamp": "2025-10-26T05:54:16.689Z",
    "event": "page_visit",
    "visitorId": "visitor_1761377512928_s98zt9ofi",
    "sessionId": "session_1761458056682_rbs31fat7",
    "referrer": "Direct",
    "userAgent": "Mozilla/5.0 (Macintosh; Intel Mac OS X 10_15_7) AppleWebKit/537.36 (KHTML, like Gecko) Chrome/141.0.0.0 Safari/537.36",
    "screenWidth": 1920,
    "screenHeight": 1080,
    "language": "en-AU",
    "hookVariant": "A"
  },
  {
    "page": "/",
    "timestamp": "2025-10-26T05:54:18.588Z",
    "event": "page_exit",
    "sessionId": "session_1761458056682_rbs31fat7",
    "duration": 2
  },
  {
    "page": "/",
    "timestamp": "2025-10-26T05:54:19.120Z",
    "event": "page_visit",
    "visitorId": "visitor_1761377512928_s98zt9ofi",
    "sessionId": "session_1761458059120_8irowcjxs",
    "referrer": "Direct",
    "userAgent": "Mozilla/5.0 (Macintosh; Intel Mac OS X 10_15_7) AppleWebKit/537.36 (KHTML, like Gecko) Chrome/141.0.0.0 Safari/537.36",
    "screenWidth": 1920,
    "screenHeight": 1080,
    "language": "en-AU",
    "hookVariant": "A"
  },
  {
    "page": "/",
    "timestamp": "2025-10-26T05:57:00.651Z",
    "event": "page_visit",
    "visitorId": "visitor_1761457745306_vvcxala8e",
    "sessionId": "session_1761458220636_wzm6yoqdt",
    "referrer": "Direct",
    "userAgent": "Mozilla/5.0 (iPhone; CPU iPhone OS 18_6_2 like Mac OS X) AppleWebKit/605.1.15 (KHTML, like Gecko) Version/18.6 Mobile/15E148 Safari/604.1",
    "screenWidth": 414,
    "screenHeight": 896,
    "language": "en-GB",
    "hookVariant": "B",
    "ipAddress": "2600:1900:0:2d02::1e01",
    "city": "Council Bluffs",
    "region": "Iowa",
    "timezone": "America/Chicago",
    "country": "United States",
    "countryCode": "US"
  },
  {
    "page": "/",
    "timestamp": "2025-10-26T05:59:33.440Z",
    "event": "page_visit",
    "visitorId": "visitor_1761457745306_vvcxala8e",
    "sessionId": "session_1761458373430_ufikcad3n",
    "referrer": "Direct",
    "userAgent": "Mozilla/5.0 (iPhone; CPU iPhone OS 18_6_2 like Mac OS X) AppleWebKit/605.1.15 (KHTML, like Gecko) Version/18.6 Mobile/15E148 Safari/604.1",
    "screenWidth": 414,
    "screenHeight": 896,
    "language": "en-GB",
    "hookVariant": "B",
    "ipAddress": "2600:1900:0:2d02::1e01",
    "city": "Council Bluffs",
    "region": "Iowa",
    "timezone": "America/Chicago",
    "country": "United States",
    "countryCode": "US"
  },
  {
    "page": "/",
    "timestamp": "2025-10-26T06:07:13.308Z",
    "event": "page_visit",
    "visitorId": "visitor_1761411933753_g5xzl3915",
    "sessionId": "session_1761458833303_0xmcu4tud",
    "referrer": "Direct",
    "userAgent": "Mozilla/5.0 (Macintosh; Intel Mac OS X 10_15_7) AppleWebKit/537.36 (KHTML, like Gecko) Chrome/141.0.0.0 Safari/537.36",
    "screenWidth": 1920,
    "screenHeight": 1080,
    "language": "en-AU",
    "hookVariant": "A"
  },
  {
    "page": "/",
    "timestamp": "2025-10-26T06:07:45.193Z",
    "event": "button_click",
    "buttonName": "Yes, I want to join The Shift Free 3 Day Challenge",
    "referrer": "Direct"
  },
  {
    "page": "/",
    "timestamp": "2025-10-26T06:07:51.640Z",
    "event": "button_click",
    "buttonName": "Join The 3-Day Mothers Challenge (FREE)",
    "referrer": "Direct"
  },
  {
    "page": "/",
    "timestamp": "2025-10-26T06:08:00.522Z",
    "event": "page_visit",
    "visitorId": "visitor_1761411933753_g5xzl3915",
    "sessionId": "session_1761458880522_gy6h0defk",
    "referrer": "Direct",
    "userAgent": "Mozilla/5.0 (Macintosh; Intel Mac OS X 10_15_7) AppleWebKit/537.36 (KHTML, like Gecko) Chrome/141.0.0.0 Safari/537.36",
    "screenWidth": 1920,
    "screenHeight": 1080,
    "language": "en-AU",
    "hookVariant": "A"
  },
  {
    "page": "/",
    "timestamp": "2025-10-26T06:09:22.957Z",
    "event": "page_visit",
    "visitorId": "visitor_1761411933753_g5xzl3915",
    "sessionId": "session_1761458962956_ud34pgnge",
    "referrer": "Direct",
    "userAgent": "Mozilla/5.0 (Macintosh; Intel Mac OS X 10_15_7) AppleWebKit/537.36 (KHTML, like Gecko) Chrome/141.0.0.0 Safari/537.36",
    "screenWidth": 1920,
    "screenHeight": 1080,
    "language": "en-AU",
    "hookVariant": "A"
  },
  {
    "page": "/",
    "timestamp": "2025-10-26T06:10:35.203Z",
    "event": "page_visit",
    "visitorId": "visitor_1761411933753_g5xzl3915",
    "sessionId": "session_1761459035203_25cm1r9v1",
    "referrer": "Direct",
    "userAgent": "Mozilla/5.0 (Macintosh; Intel Mac OS X 10_15_7) AppleWebKit/537.36 (KHTML, like Gecko) Chrome/141.0.0.0 Safari/537.36",
    "screenWidth": 1920,
    "screenHeight": 1080,
    "language": "en-AU",
    "hookVariant": "A"
  },
  {
    "page": "/",
    "timestamp": "2025-10-26T06:10:53.923Z",
    "event": "page_visit",
    "visitorId": "visitor_1761411933753_g5xzl3915",
    "sessionId": "session_1761459053922_k2mqnzlj2",
    "referrer": "Direct",
    "userAgent": "Mozilla/5.0 (Macintosh; Intel Mac OS X 10_15_7) AppleWebKit/537.36 (KHTML, like Gecko) Chrome/141.0.0.0 Safari/537.36",
    "screenWidth": 1920,
    "screenHeight": 1080,
    "language": "en-AU",
    "hookVariant": "A"
  },
  {
    "page": "/",
    "timestamp": "2025-10-26T06:11:00.507Z",
    "event": "page_visit",
    "visitorId": "visitor_1761411933753_g5xzl3915",
    "sessionId": "session_1761459060507_4q07yt4qp",
    "referrer": "Direct",
    "userAgent": "Mozilla/5.0 (Macintosh; Intel Mac OS X 10_15_7) AppleWebKit/537.36 (KHTML, like Gecko) Chrome/141.0.0.0 Safari/537.36",
    "screenWidth": 1920,
    "screenHeight": 1080,
    "language": "en-AU",
    "hookVariant": "A"
  },
  {
    "page": "/",
    "timestamp": "2025-10-26T06:11:13.064Z",
    "event": "page_visit",
    "visitorId": "visitor_1761411933753_g5xzl3915",
    "sessionId": "session_1761459073063_iiyuhxw73",
    "referrer": "Direct",
    "userAgent": "Mozilla/5.0 (Macintosh; Intel Mac OS X 10_15_7) AppleWebKit/537.36 (KHTML, like Gecko) Chrome/141.0.0.0 Safari/537.36",
    "screenWidth": 1920,
    "screenHeight": 1080,
    "language": "en-AU",
    "hookVariant": "A",
    "ipAddress": "49.36.180.216",
    "city": "New Delhi",
    "region": "National Capital Territory of Delhi",
    "timezone": "Asia/Kolkata",
    "country": "India",
    "countryCode": "IN"
  },
  {
    "page": "/",
    "timestamp": "2025-10-26T06:11:57.738Z",
    "event": "page_visit",
    "visitorId": "visitor_1761411933753_g5xzl3915",
    "sessionId": "session_1761459117737_ty2d7eqcl",
    "referrer": "Direct",
    "userAgent": "Mozilla/5.0 (Macintosh; Intel Mac OS X 10_15_7) AppleWebKit/537.36 (KHTML, like Gecko) Chrome/141.0.0.0 Safari/537.36",
    "screenWidth": 1920,
    "screenHeight": 1080,
    "language": "en-AU",
    "hookVariant": "A",
    "ipAddress": "49.36.180.216",
    "city": "New Delhi",
    "region": "National Capital Territory of Delhi",
    "timezone": "Asia/Kolkata",
    "country": "India",
    "countryCode": "IN"
  },
  {
    "page": "/",
    "timestamp": "2025-10-26T06:12:16.170Z",
    "event": "page_visit",
    "visitorId": "visitor_1761411933753_g5xzl3915",
    "sessionId": "session_1761459136169_u9q5rtxvt",
    "referrer": "Direct",
    "userAgent": "Mozilla/5.0 (Macintosh; Intel Mac OS X 10_15_7) AppleWebKit/537.36 (KHTML, like Gecko) Chrome/141.0.0.0 Safari/537.36",
    "screenWidth": 1920,
    "screenHeight": 1080,
    "language": "en-AU",
    "hookVariant": "A",
    "ipAddress": "49.36.180.216",
    "city": "New Delhi",
    "region": "National Capital Territory of Delhi",
    "timezone": "Asia/Kolkata",
    "country": "India",
    "countryCode": "IN"
  },
  {
    "page": "/",
    "timestamp": "2025-10-26T06:12:42.498Z",
    "event": "button_click",
    "buttonName": "Join The 3-Day Mothers Challenge (FREE)",
    "referrer": "Direct"
  },
  {
    "page": "/",
    "timestamp": "2025-10-26T06:16:22.972Z",
    "event": "page_visit",
    "visitorId": "visitor_1761377512928_s98zt9ofi",
    "sessionId": "session_1761459382969_c73ffz3nw",
    "referrer": "Direct",
    "userAgent": "Mozilla/5.0 (Macintosh; Intel Mac OS X 10_15_7) AppleWebKit/537.36 (KHTML, like Gecko) Chrome/141.0.0.0 Safari/537.36",
    "screenWidth": 1920,
    "screenHeight": 1080,
    "language": "en-AU",
    "hookVariant": "A",
    "ipAddress": "2600:1900:0:2d02::1d00",
    "city": "Council Bluffs",
    "region": "Iowa",
    "timezone": "America/Chicago",
    "country": "United States",
    "countryCode": "US"
  },
  {
    "page": "/",
    "timestamp": "2025-10-26T06:17:20.572Z",
    "event": "page_visit",
    "visitorId": "visitor_1761411933753_g5xzl3915",
    "sessionId": "session_1761459440572_v1mww5w34",
    "referrer": "Direct",
    "userAgent": "Mozilla/5.0 (Macintosh; Intel Mac OS X 10_15_7) AppleWebKit/537.36 (KHTML, like Gecko) Chrome/141.0.0.0 Safari/537.36",
    "screenWidth": 1920,
    "screenHeight": 1080,
    "language": "en-AU",
    "hookVariant": "A"
  },
  {
    "page": "/",
    "timestamp": "2025-10-26T06:17:26.630Z",
    "event": "page_visit",
    "visitorId": "visitor_1761411933753_g5xzl3915",
    "sessionId": "session_1761459446625_stitt0t15",
    "referrer": "Direct",
    "userAgent": "Mozilla/5.0 (Macintosh; Intel Mac OS X 10_15_7) AppleWebKit/537.36 (KHTML, like Gecko) Chrome/141.0.0.0 Safari/537.36",
    "screenWidth": 1920,
    "screenHeight": 1080,
    "language": "en-AU",
    "hookVariant": "A"
  },
  {
    "page": "/",
    "timestamp": "2025-10-26T06:17:28.595Z",
    "event": "page_visit",
    "visitorId": "visitor_1761411933753_g5xzl3915",
    "sessionId": "session_1761459448591_yp236c140",
    "referrer": "Direct",
    "userAgent": "Mozilla/5.0 (Macintosh; Intel Mac OS X 10_15_7) AppleWebKit/537.36 (KHTML, like Gecko) Chrome/141.0.0.0 Safari/537.36",
    "screenWidth": 1920,
    "screenHeight": 1080,
    "language": "en-AU",
    "hookVariant": "A",
    "ipAddress": "49.36.180.216",
    "city": "New Delhi",
    "region": "National Capital Territory of Delhi",
    "timezone": "Asia/Kolkata",
    "country": "India",
    "countryCode": "IN"
  },
  {
    "page": "/",
    "timestamp": "2025-10-26T06:18:11.035Z",
    "event": "page_visit",
    "visitorId": "visitor_1761411933753_g5xzl3915",
    "sessionId": "session_1761459491035_hq7upp0v1",
    "referrer": "Direct",
    "userAgent": "Mozilla/5.0 (Macintosh; Intel Mac OS X 10_15_7) AppleWebKit/537.36 (KHTML, like Gecko) Chrome/141.0.0.0 Safari/537.36",
    "screenWidth": 1920,
    "screenHeight": 1080,
    "language": "en-AU",
    "hookVariant": "A"
  },
  {
    "page": "/",
    "timestamp": "2025-10-26T06:18:15.615Z",
    "event": "page_visit",
    "visitorId": "visitor_1761411933753_g5xzl3915",
    "sessionId": "session_1761459495615_9b0pzbf3u",
    "referrer": "Direct",
    "userAgent": "Mozilla/5.0 (Macintosh; Intel Mac OS X 10_15_7) AppleWebKit/537.36 (KHTML, like Gecko) Chrome/141.0.0.0 Safari/537.36",
    "screenWidth": 1920,
    "screenHeight": 1080,
    "language": "en-AU",
    "hookVariant": "A",
    "ipAddress": "49.36.180.216",
    "city": "New Delhi",
    "region": "National Capital Territory of Delhi",
    "timezone": "Asia/Kolkata",
    "country": "India",
    "countryCode": "IN"
  },
  {
    "page": "/",
    "timestamp": "2025-10-26T06:18:47.553Z",
    "event": "page_visit",
    "visitorId": "visitor_1761411933753_g5xzl3915",
    "sessionId": "session_1761459527552_6sezj4285",
    "referrer": "Direct",
    "userAgent": "Mozilla/5.0 (Macintosh; Intel Mac OS X 10_15_7) AppleWebKit/537.36 (KHTML, like Gecko) Chrome/141.0.0.0 Safari/537.36",
    "screenWidth": 1920,
    "screenHeight": 1080,
    "language": "en-AU",
    "hookVariant": "A"
  },
  {
    "page": "/",
    "timestamp": "2025-10-26T06:20:34.639Z",
    "event": "page_visit",
    "visitorId": "visitor_1761411933753_g5xzl3915",
    "sessionId": "session_1761459634638_q1n8ohad5",
    "referrer": "Direct",
    "userAgent": "Mozilla/5.0 (Macintosh; Intel Mac OS X 10_15_7) AppleWebKit/537.36 (KHTML, like Gecko) Chrome/141.0.0.0 Safari/537.36",
    "screenWidth": 1920,
    "screenHeight": 1080,
    "language": "en-AU",
    "hookVariant": "A"
  },
  {
    "page": "/",
    "timestamp": "2025-10-26T06:20:37.352Z",
    "event": "page_visit",
    "visitorId": "visitor_1761411933753_g5xzl3915",
    "sessionId": "session_1761459637326_t9brkplvp",
    "referrer": "Direct",
    "userAgent": "Mozilla/5.0 (Macintosh; Intel Mac OS X 10_15_7) AppleWebKit/537.36 (KHTML, like Gecko) Chrome/141.0.0.0 Safari/537.36",
    "screenWidth": 1920,
    "screenHeight": 1080,
    "language": "en-AU",
    "hookVariant": "A"
  },
  {
    "page": "/",
    "timestamp": "2025-10-26T06:21:33.527Z",
    "event": "button_click",
    "buttonName": "Join The 3-Day Mothers Challenge (FREE)",
    "referrer": "Direct"
  },
  {
    "page": "/",
    "timestamp": "2025-10-26T06:22:44.368Z",
    "event": "page_visit",
    "visitorId": "visitor_1761411933753_g5xzl3915",
    "sessionId": "session_1761459764367_rzbfc41d8",
    "referrer": "Direct",
    "userAgent": "Mozilla/5.0 (Macintosh; Intel Mac OS X 10_15_7) AppleWebKit/537.36 (KHTML, like Gecko) Chrome/141.0.0.0 Safari/537.36",
    "screenWidth": 1920,
    "screenHeight": 1080,
    "language": "en-AU",
    "hookVariant": "A",
    "ipAddress": "49.36.180.216",
    "city": "New Delhi",
    "region": "National Capital Territory of Delhi",
    "timezone": "Asia/Kolkata",
    "country": "India",
    "countryCode": "IN"
  },
  {
    "page": "/",
    "timestamp": "2025-10-26T06:22:57.988Z",
    "event": "page_visit",
    "visitorId": "visitor_1761411933753_g5xzl3915",
    "sessionId": "session_1761459777988_i7fktiufi",
    "referrer": "Direct",
    "userAgent": "Mozilla/5.0 (Macintosh; Intel Mac OS X 10_15_7) AppleWebKit/537.36 (KHTML, like Gecko) Chrome/141.0.0.0 Safari/537.36",
    "screenWidth": 1920,
    "screenHeight": 1080,
    "language": "en-AU",
    "hookVariant": "A",
    "ipAddress": "49.36.180.216",
    "city": "New Delhi",
    "region": "National Capital Territory of Delhi",
    "timezone": "Asia/Kolkata",
    "country": "India",
    "countryCode": "IN"
  },
  {
    "page": "/",
    "timestamp": "2025-10-26T06:23:43.356Z",
    "event": "page_visit",
    "visitorId": "visitor_1761411933753_g5xzl3915",
    "sessionId": "session_1761459823355_5zndf7qmr",
    "referrer": "Direct",
    "userAgent": "Mozilla/5.0 (Macintosh; Intel Mac OS X 10_15_7) AppleWebKit/537.36 (KHTML, like Gecko) Chrome/141.0.0.0 Safari/537.36",
    "screenWidth": 1920,
    "screenHeight": 1080,
    "language": "en-AU",
    "hookVariant": "A",
    "ipAddress": "49.36.180.216",
    "city": "New Delhi",
    "region": "National Capital Territory of Delhi",
    "timezone": "Asia/Kolkata",
    "country": "India",
    "countryCode": "IN"
  },
  {
    "page": "/",
    "timestamp": "2025-10-26T06:24:39.473Z",
    "event": "page_visit",
    "visitorId": "visitor_1761411933753_g5xzl3915",
    "sessionId": "session_1761459879472_1wok97z0p",
    "referrer": "Direct",
    "userAgent": "Mozilla/5.0 (Macintosh; Intel Mac OS X 10_15_7) AppleWebKit/537.36 (KHTML, like Gecko) Chrome/141.0.0.0 Safari/537.36",
    "screenWidth": 1920,
    "screenHeight": 1080,
    "language": "en-AU",
    "hookVariant": "A",
    "ipAddress": "49.36.180.216",
    "city": "New Delhi",
    "region": "National Capital Territory of Delhi",
    "timezone": "Asia/Kolkata",
    "country": "India",
    "countryCode": "IN"
  },
  {
    "page": "/",
    "timestamp": "2025-10-26T06:27:36.143Z",
    "event": "page_visit",
    "visitorId": "visitor_1761460056140_v7l6hqo14",
    "sessionId": "session_1761460056140_cgdqc62xc",
    "referrer": "Direct",
    "userAgent": "Mozilla/5.0 (Windows NT 10.0; Win64; x64) AppleWebKit/537.36 (KHTML, like Gecko) Chrome/141.0.0.0 Safari/537.36",
    "screenWidth": 1920,
    "screenHeight": 1080,
    "language": "en-US",
    "hookVariant": "A",
    "ipAddress": "2600:1900:0:2d02::3201",
    "city": "Council Bluffs",
    "region": "Iowa",
    "timezone": "America/Chicago",
    "country": "United States",
    "countryCode": "US"
  },
  {
    "page": "/",
    "timestamp": "2025-10-26T06:27:42.782Z",
    "event": "button_click",
    "buttonName": "Join The 3-Day Mothers Challenge (FREE)",
    "referrer": "Direct"
  },
  {
    "page": "/",
    "timestamp": "2025-10-26T06:27:51.042Z",
    "event": "button_click",
    "buttonName": "Yes, I want to join The Shift Free 3 Day Challenge",
    "referrer": "Direct"
  },
  {
    "page": "/",
    "timestamp": "2025-10-26T06:28:25.927Z",
    "event": "button_click",
    "buttonName": "Register now",
    "referrer": "Direct"
  },
  {
    "page": "/index.html",
    "timestamp": "2025-10-26T06:28:27.440Z",
    "event": "registration",
    "email": "faiza.naseem1984@yahoo.com",
    "name": "Faiza Naseem",
    "firstName": "Faiza",
    "lastName": "Naseem",
    "country": "Australia",
    "city": "",
    "source": "Registration Form - The Shift Landing Page",
    "clickfunnelsSuccess": true,
    "hookVariant": "A",
    "visitorId": "visitor_1761460056140_v7l6hqo14"
  },
  {
    "page": "/",
    "timestamp": "2025-10-26T06:28:29.782Z",
    "event": "page_exit",
    "sessionId": "session_1761460056140_cgdqc62xc",
    "duration": 54
  },
  {
    "page": "/",
    "timestamp": "2025-10-26T06:29:02.152Z",
    "event": "page_exit",
    "sessionId": "session_1761459382969_c73ffz3nw",
    "duration": 94
  },
  {
    "page": "/",
    "timestamp": "2025-10-26T06:29:03.710Z",
    "event": "page_visit",
    "visitorId": "visitor_1761377512928_s98zt9ofi",
    "sessionId": "session_1761460143709_2oxo8a67n",
    "referrer": "Direct",
    "userAgent": "Mozilla/5.0 (Macintosh; Intel Mac OS X 10_15_7) AppleWebKit/537.36 (KHTML, like Gecko) Chrome/141.0.0.0 Safari/537.36",
    "screenWidth": 1920,
    "screenHeight": 1080,
    "language": "en-AU",
    "hookVariant": "A"
  },
  {
    "page": "/",
    "timestamp": "2025-10-26T06:32:09.367Z",
    "event": "page_visit",
    "visitorId": "visitor_1761460329362_ho72mr13g",
    "sessionId": "session_1761460329363_no12kerpj",
    "referrer": "android-app://com.google.android.gm/",
    "userAgent": "Mozilla/5.0 (Linux; Android 10; K) AppleWebKit/537.36 (KHTML, like Gecko) Chrome/141.0.0.0 Mobile Safari/537.36",
    "screenWidth": 412,
    "screenHeight": 869,
    "language": "en-GB",
    "hookVariant": "A",
    "email": "nassrine_rifia@hotmail.fr",
    "name": "Soriya"
  },
  {
    "page": "/",
    "timestamp": "2025-10-26T06:32:26.297Z",
    "event": "button_click",
    "buttonName": "Join The 3-Day Mothers Challenge (FREE)",
    "referrer": "android-app://com.google.android.gm/"
  },
  {
    "page": "/",
    "timestamp": "2025-10-26T06:32:32.870Z",
    "event": "button_click",
    "buttonName": "Register now",
    "referrer": "android-app://com.google.android.gm/"
  },
  {
    "page": "/index.html",
    "timestamp": "2025-10-26T06:32:34.405Z",
    "event": "registration",
    "email": "nassrine_rifia@hotmail.fr",
    "name": "Soriya",
    "firstName": "Soriya",
    "lastName": "",
    "country": "United Kingdom",
    "city": "",
    "source": "Registration Form - The Shift Landing Page",
    "clickfunnelsSuccess": true,
    "hookVariant": "A",
    "visitorId": "visitor_1761460329362_ho72mr13g"
  },
  {
    "page": "/",
    "timestamp": "2025-10-26T06:32:36.598Z",
    "event": "page_exit",
    "sessionId": "session_1761460329363_no12kerpj",
    "duration": 27
  },
  {
    "page": "/",
    "timestamp": "2025-10-26T06:51:55.555Z",
    "event": "page_visit",
    "visitorId": "visitor_1761461515553_krktt0f3a",
    "sessionId": "session_1761461515553_06j6zyzzt",
    "referrer": "Direct",
    "userAgent": "Mozilla/5.0 (Windows NT 10.0; Win64; x64) AppleWebKit/537.36 (KHTML, like Gecko) Chrome/125.0.0.0 Safari/537.3",
    "screenWidth": 1280,
    "screenHeight": 1696,
    "language": "en-US",
    "hookVariant": "B",
    "ipAddress": "2600:1900:0:2d02::3201",
    "city": "Council Bluffs",
    "region": "Iowa",
    "timezone": "America/Chicago",
    "country": "United States",
    "countryCode": "US"
  },
  {
    "page": "/",
    "timestamp": "2025-10-26T06:58:06.953Z",
    "event": "page_visit",
    "visitorId": "visitor_1761461886939_650p9eblw",
    "sessionId": "session_1761461886940_p9z4prnhc",
    "referrer": "Direct",
    "userAgent": "Mozilla/5.0 (Linux; Android 10; K) AppleWebKit/537.36 (KHTML, like Gecko) Chrome/141.0.0.0 Mobile Safari/537.36",
    "screenWidth": 412,
    "screenHeight": 915,
    "language": "nl-NL",
    "hookVariant": "A",
    "email": "nmarkouchi@yahoo.com",
    "name": "Naima",
    "ipAddress": "2600:1900:0:2d02::3201",
    "city": "Council Bluffs",
    "region": "Iowa",
    "timezone": "America/Chicago",
    "country": "United States",
    "countryCode": "US"
  },
  {
    "page": "/index.html",
    "timestamp": "2025-10-26T07:00:15.642Z",
    "event": "registration",
    "email": "nmarkouchi@yahoo.com",
    "name": "Naima",
    "firstName": "Naima",
    "lastName": "",
    "country": "Netherlands",
    "city": "",
    "source": "Registration Form - The Shift Landing Page",
    "clickfunnelsSuccess": true,
    "hookVariant": "A",
    "visitorId": "visitor_1761461886939_650p9eblw"
  },
  {
    "page": "/upsell.html",
    "timestamp": "2025-10-26T07:00:18.138Z",
    "event": "page_visit",
    "visitorId": "visitor_1761461886939_650p9eblw",
    "sessionId": "session_1761462018134_imlgz35k4",
    "referrer": "https://momsshift.com/?name=Naima&email=nmarkouchi@yahoo.com",
    "userAgent": "Mozilla/5.0 (Linux; Android 10; K) AppleWebKit/537.36 (KHTML, like Gecko) Chrome/141.0.0.0 Mobile Safari/537.36",
    "screenWidth": 412,
    "screenHeight": 915,
    "language": "nl-NL",
    "email": "nmarkouchi@yahoo.com",
    "name": "Naima",
    "ipAddress": "2600:1900:0:2d02::3201",
    "city": "Council Bluffs",
    "region": "Iowa",
    "timezone": "America/Chicago",
    "country": "Netherlands"
  },
  {
    "page": "/upsell.html",
    "timestamp": "2025-10-26T07:02:23.046Z",
    "event": "page_exit",
    "sessionId": "session_1761462018134_imlgz35k4",
    "duration": 125
  },
  {
    "page": "/",
    "timestamp": "2025-10-26T07:10:18.237Z",
    "event": "page_visit",
    "visitorId": "visitor_1761462618233_igx6xpnin",
    "sessionId": "session_1761462618233_5hq5kn7en",
    "referrer": "Direct",
    "userAgent": "Mozilla/5.0 (Linux; Android 10; K) AppleWebKit/537.36 (KHTML, like Gecko) Chrome/141.0.0.0 Mobile Safari/537.36",
    "screenWidth": 360,
    "screenHeight": 780,
    "language": "en-GB",
    "hookVariant": "A",
    "email": "masarat.malik@hotmail.co.uk",
    "name": "Masarat",
    "ipAddress": "2600:1900:0:2d02::3201",
    "city": "Council Bluffs",
    "region": "Iowa",
    "timezone": "America/Chicago",
    "country": "United States",
    "countryCode": "US"
  },
  {
    "page": "/",
    "timestamp": "2025-10-26T07:10:22.263Z",
    "event": "page_visit",
    "visitorId": "visitor_1761462622259_ym7ty1lja",
    "sessionId": "session_1761462622260_vgp1orpe7",
    "referrer": "Direct",
    "userAgent": "Mozilla/5.0 (Linux; Android 10; K) AppleWebKit/537.36 (KHTML, like Gecko) Chrome/138.0.0.0 Mobile Safari/537.36 (compatible; Google-Read-Aloud; +https://support.google.com/webmasters/answer/1061943)",
    "screenWidth": 400,
    "screenHeight": 400,
    "language": "en-US",
    "hookVariant": "B",
    "email": "masarat.malik@hotmail.co.uk",
    "name": "Masarat",
    "ipAddress": "2600:1900:0:2d02::3201",
    "city": "Council Bluffs",
    "region": "Iowa",
    "timezone": "America/Chicago",
    "country": "United States",
    "countryCode": "US"
  },
  {
    "page": "/",
    "timestamp": "2025-10-26T07:11:17.643Z",
    "event": "page_visit",
    "visitorId": "visitor_1761462618233_igx6xpnin",
    "sessionId": "session_1761462677640_xruqblzhv",
    "referrer": "Direct",
    "userAgent": "Mozilla/5.0 (Linux; Android 10; K) AppleWebKit/537.36 (KHTML, like Gecko) Chrome/141.0.0.0 Mobile Safari/537.36",
    "screenWidth": 360,
    "screenHeight": 780,
    "language": "en-GB",
    "hookVariant": "A",
    "email": "masarat.malik@hotmail.co.uk",
    "name": "Masarat",
    "ipAddress": "2600:1900:0:2d02::3201",
    "city": "Council Bluffs",
    "region": "Iowa",
    "timezone": "America/Chicago",
    "country": "United States",
    "countryCode": "US"
  },
  {
    "page": "/",
    "timestamp": "2025-10-26T07:20:18.368Z",
    "event": "page_visit",
    "visitorId": "visitor_1761463218350_0hbspn3mt",
    "sessionId": "session_1761463218350_q36jg7ras",
    "referrer": "Direct",
    "userAgent": "Mozilla/5.0 (iPhone; CPU iPhone OS 18_6_2 like Mac OS X) AppleWebKit/605.1.15 (KHTML, like Gecko) CriOS/141.0.7390.96 Mobile/15E148 Safari/604.1",
    "screenWidth": 390,
    "screenHeight": 844,
    "language": "nl-NL",
    "hookVariant": "B"
  },
  {
    "page": "/",
    "timestamp": "2025-10-26T07:42:07.112Z",
    "event": "page_visit",
    "visitorId": "visitor_1761463218350_0hbspn3mt",
    "sessionId": "session_1761464527109_vnkd3wlvs",
    "referrer": "Direct",
    "userAgent": "Mozilla/5.0 (iPhone; CPU iPhone OS 18_6_2 like Mac OS X) AppleWebKit/605.1.15 (KHTML, like Gecko) CriOS/141.0.7390.96 Mobile/15E148 Safari/604.1",
    "screenWidth": 390,
    "screenHeight": 844,
    "language": "nl-NL",
    "hookVariant": "B"
  },
  {
    "page": "/",
    "timestamp": "2025-10-26T09:19:18.481Z",
    "event": "page_visit",
    "visitorId": "visitor_1761470358477_heeskqj8m",
    "sessionId": "session_1761470358477_sqm8s8yxn",
    "referrer": "Direct",
    "userAgent": "Mozilla/5.0 (iPhone; CPU iPhone OS 18_3_2 like Mac OS X) AppleWebKit/605.1.15 (KHTML, like Gecko) Version/18.3.1 Mobile/15E148 Safari/604.1",
    "screenWidth": 390,
    "screenHeight": 844,
    "language": "en-GB",
    "hookVariant": "A",
    "ipAddress": "2600:1900:0:2d02::3201",
    "city": "Council Bluffs",
    "region": "Iowa",
    "timezone": "America/Chicago",
    "country": "United States",
    "countryCode": "US"
  },
  {
    "page": "/",
    "timestamp": "2025-10-26T09:20:18.135Z",
    "event": "button_click",
    "buttonName": "Join The 3-Day Mothers Challenge (FREE)",
    "referrer": "Direct"
  },
  {
    "page": "/",
    "timestamp": "2025-10-26T09:21:29.738Z",
    "event": "button_click",
    "buttonName": "Register now",
    "referrer": "Direct"
  },
  {
    "page": "/index.html",
    "timestamp": "2025-10-26T09:21:30.984Z",
    "event": "registration",
    "email": "adeebarani@hotmail.co.uk",
    "name": "Adeeba Rani",
    "firstName": "Adeeba",
    "lastName": "Rani",
    "country": "United Kingdom",
    "city": "Council Bluffs",
    "source": "Registration Form - The Shift Landing Page",
    "clickfunnelsSuccess": true,
    "hookVariant": "A",
    "visitorId": "visitor_1761470358477_heeskqj8m"
  },
  {
    "page": "/upsell.html",
    "timestamp": "2025-10-26T09:21:33.448Z",
    "event": "page_visit",
    "visitorId": "visitor_1761470358477_heeskqj8m",
    "sessionId": "session_1761470493447_lazqflj10",
    "referrer": "https://momsshift.com/",
    "userAgent": "Mozilla/5.0 (iPhone; CPU iPhone OS 18_3_2 like Mac OS X) AppleWebKit/605.1.15 (KHTML, like Gecko) Version/18.3.1 Mobile/15E148 Safari/604.1",
    "screenWidth": 390,
    "screenHeight": 844,
    "language": "en-GB",
    "email": "adeebarani@hotmail.co.uk",
    "name": "Adeeba",
    "ipAddress": "2600:1900:0:2d02::3201",
    "city": "Council Bluffs",
    "region": "Iowa",
    "timezone": "America/Chicago",
    "country": "United Kingdom"
  },
  {
    "page": "/",
    "timestamp": "2025-10-26T09:24:21.537Z",
    "event": "page_visit",
    "visitorId": "visitor_1761470661536_s74njzjgn",
    "sessionId": "session_1761470661537_rpccs3df9",
    "referrer": "Direct",
    "userAgent": "Mozilla/5.0 (iPhone; CPU iPhone OS 18_6_2 like Mac OS X) AppleWebKit/605.1.15 (KHTML, like Gecko) CriOS/141.0.7390.96 Mobile/15E148 Safari/604.1",
    "screenWidth": 390,
    "screenHeight": 844,
    "language": "tr-TR",
    "hookVariant": "A",
    "ipAddress": "2600:1900:0:2d02::3201",
    "city": "Council Bluffs",
    "region": "Iowa",
    "timezone": "America/Chicago",
    "country": "United States",
    "countryCode": "US"
  },
  {
    "page": "/thank-you.html",
    "timestamp": "2025-10-26T09:26:15.463Z",
    "event": "page_visit",
    "visitorId": "visitor_1761470358477_heeskqj8m",
    "sessionId": "session_1761470775463_ef5j1z72v",
    "referrer": "https://momsshift.com/upsell.html?email=adeebarani%40hotmail.co.uk&name=Adeeba&country=United%20Kingdom&variant=A",
    "userAgent": "Mozilla/5.0 (iPhone; CPU iPhone OS 18_3_2 like Mac OS X) AppleWebKit/605.1.15 (KHTML, like Gecko) Version/18.3.1 Mobile/15E148 Safari/604.1",
    "screenWidth": 390,
    "screenHeight": 844,
    "language": "en-GB"
  },
  {
    "page": "/",
    "timestamp": "2025-10-26T09:48:23.787Z",
    "event": "page_visit",
    "visitorId": "visitor_1761472103786_7ywktkvnj",
    "sessionId": "session_1761472103786_7fo8fmqoz",
    "referrer": "Direct",
    "userAgent": "Mozilla/5.0 (iPhone; CPU iPhone OS 18_7_1 like Mac OS X) AppleWebKit/605.1.15 (KHTML, like Gecko) Version/18.7 Mobile/15E148 Safari/604.1",
    "screenWidth": 430,
    "screenHeight": 932,
    "language": "en-US",
    "hookVariant": "A",
    "email": "ebrahim_reyhana@yahoo.com.au"
  },
  {
    "page": "/upsell.html",
    "timestamp": "2025-10-26T09:58:46.876Z",
    "event": "page_visit",
    "visitorId": "visitor_1761398385160_7y6h7ghmp",
    "sessionId": "session_1761472726860_x442732pq",
    "referrer": "https://momsshift.com/",
    "userAgent": "Mozilla/5.0 (Linux; Android 10; K) AppleWebKit/537.36 (KHTML, like Gecko) Chrome/113.0.0.0 Mobile Safari/537.36",
    "screenWidth": 360,
    "screenHeight": 820,
    "language": "en-US",
    "email": "ruqayatadeleke@gmail.com",
    "name": "Olanipekun",
    "ipAddress": "2600:1900:0:2d02::3201",
    "city": "Council Bluffs",
    "region": "Iowa",
    "timezone": "America/Chicago",
    "country": "Nigeria"
  },
  {
    "page": "/",
    "timestamp": "2025-10-26T10:03:12.676Z",
    "event": "page_visit",
    "visitorId": "visitor_1761472992672_u3onda3po",
    "sessionId": "session_1761472992673_4na5q1mpw",
    "referrer": "android-app://com.google.android.gm/",
    "userAgent": "Mozilla/5.0 (Linux; Android 10; K) AppleWebKit/537.36 (KHTML, like Gecko) SamsungBrowser/28.0 Chrome/130.0.0.0 Mobile Safari/537.36",
    "screenWidth": 412,
    "screenHeight": 869,
    "language": "en-GB",
    "hookVariant": "B",
    "ipAddress": "2600:1900:0:2d02::3201",
    "city": "Council Bluffs",
    "region": "Iowa",
    "timezone": "America/Chicago",
    "country": "United States",
    "countryCode": "US"
  },
  {
    "page": "/",
    "timestamp": "2025-10-26T10:08:39.443Z",
    "event": "page_visit",
    "visitorId": "visitor_1761473319264_5q5zp6o1x",
    "sessionId": "session_1761473319264_56nz9xc6b",
    "referrer": "Direct",
    "userAgent": "Mozilla/5.0 (Macintosh; Intel Mac OS X 10_15_7) AppleWebKit/537.36 (KHTML, like Gecko) Chrome/108.0.0.0 Safari/537.36",
    "screenWidth": 800,
    "screenHeight": 600,
    "language": "en-US",
    "hookVariant": "A"
  },
  {
    "page": "/",
    "timestamp": "2025-10-26T10:08:40.920Z",
    "event": "page_exit",
    "sessionId": "session_1761473319264_56nz9xc6b",
    "duration": 1
  },
  {
    "page": "/",
    "timestamp": "2025-10-26T10:16:44.168Z",
    "event": "page_visit",
    "visitorId": "visitor_1761473804073_orlp1ox96",
    "sessionId": "session_1761473804074_7w3faqjfi",
    "referrer": "Direct",
    "userAgent": "Mozilla/5.0 (Macintosh; Intel Mac OS X 10_15_7) AppleWebKit/537.36 (KHTML, like Gecko) Chrome/108.0.0.0 Safari/537.36",
    "screenWidth": 800,
    "screenHeight": 600,
    "language": "en-US",
    "hookVariant": "B",
    "ipAddress": "2600:1900:0:2d02::3201",
    "city": "Council Bluffs",
    "region": "Iowa",
    "timezone": "America/Chicago",
    "country": "United States",
    "countryCode": "US"
  },
  {
    "page": "/",
    "timestamp": "2025-10-26T10:17:08.358Z",
    "event": "page_exit",
    "sessionId": "session_1761473804074_7w3faqjfi",
    "duration": 24
  },
  {
    "page": "/",
    "timestamp": "2025-10-26T10:46:53.547Z",
    "event": "page_visit",
    "visitorId": "visitor_1761475613545_xzyg6n6e8",
    "sessionId": "session_1761475613545_tdg5dff5g",
    "referrer": "Direct",
    "userAgent": "Mozilla/5.0 (Macintosh; Intel Mac OS X 10_15_7) AppleWebKit/537.36 (KHTML, like Gecko) Chrome/108.0.0.0 Safari/537.36",
    "screenWidth": 800,
    "screenHeight": 600,
    "language": "en-US",
    "hookVariant": "A",
    "ipAddress": "2600:1900:0:2d02::3201",
    "city": "Council Bluffs",
    "region": "Iowa",
    "timezone": "America/Chicago",
    "country": "United States",
    "countryCode": "US"
  },
  {
    "page": "/",
    "timestamp": "2025-10-26T10:51:35.679Z",
    "event": "page_visit",
    "visitorId": "visitor_1761475895665_qqofea08z",
    "sessionId": "session_1761475895667_01ajtyby4",
    "referrer": "Direct",
    "userAgent": "Mozilla/5.0 (Windows NT 10.0; Win64; x64) AppleWebKit/537.36 (KHTML, like Gecko) Chrome/135.0.0.0 Safari/537.36",
    "screenWidth": 1920,
    "screenHeight": 1080,
    "language": "en-US",
    "hookVariant": "A",
    "ipAddress": "2600:1900:0:2d02::3201",
    "city": "Council Bluffs",
    "region": "Iowa",
    "timezone": "America/Chicago",
    "country": "United States",
    "countryCode": "US"
  },
  {
    "page": "/",
    "timestamp": "2025-10-26T10:52:03.310Z",
    "event": "page_visit",
    "visitorId": "visitor_1761475923303_0wke0r2zt",
    "sessionId": "session_1761475923304_i9fbjlkng",
    "referrer": "Direct",
    "userAgent": "Mozilla/5.0 (Windows NT 10.0; Win64; x64) AppleWebKit/537.36 (KHTML, like Gecko) Chrome/135.0.0.0 Safari/537.36",
    "screenWidth": 1920,
    "screenHeight": 1080,
    "language": "en-US",
    "hookVariant": "A"
  },
  {
    "page": "/",
    "timestamp": "2025-10-26T11:02:33.994Z",
    "event": "page_visit",
    "visitorId": "visitor_1761476553978_wzn1xzej3",
    "sessionId": "session_1761476553982_2q6y1a3t1",
    "referrer": "Direct",
    "userAgent": "Mozilla/5.0 (Linux; Android 10; K) AppleWebKit/537.36 (KHTML, like Gecko) SamsungBrowser/28.0 Chrome/130.0.0.0 Mobile Safari/537.36",
    "screenWidth": 412,
    "screenHeight": 846,
    "language": "en-NZ",
    "hookVariant": "A"
  },
  {
    "page": "/",
    "timestamp": "2025-10-26T11:16:13.781Z",
    "event": "page_visit",
    "visitorId": "visitor_1761477373779_u4yem2vkm",
    "sessionId": "session_1761477373779_e371c7lc5",
    "referrer": "Direct",
    "userAgent": "Mozilla/5.0 (iPhone; CPU iPhone OS 18_6_2 like Mac OS X) AppleWebKit/605.1.15 (KHTML, like Gecko) Version/18.6 Mobile/15E148 Safari/604.1",
    "screenWidth": 390,
    "screenHeight": 844,
    "language": "en-GB",
    "hookVariant": "A"
  },
  {
    "page": "/",
    "timestamp": "2025-10-26T11:17:23.809Z",
    "event": "button_click",
    "buttonName": "Join The 3-Day Mothers Challenge (FREE)",
    "referrer": "Direct"
  },
  {
    "page": "/",
    "timestamp": "2025-10-26T11:18:27.759Z",
    "event": "button_click",
    "buttonName": "Register now",
    "referrer": "Direct"
  },
  {
    "page": "/index.html",
    "timestamp": "2025-10-26T11:18:28.954Z",
    "event": "registration",
    "email": "bilkisum@hotmail.com",
    "name": "Bilkisu ",
    "firstName": "Bilkisu",
    "lastName": "",
    "country": "United Kingdom",
    "city": "",
    "source": "Registration Form - The Shift Landing Page",
    "clickfunnelsSuccess": true,
    "hookVariant": "A",
    "visitorId": "visitor_1761477373779_u4yem2vkm"
  },
  {
    "page": "/upsell.html",
    "timestamp": "2025-10-26T11:18:31.296Z",
    "event": "page_visit",
    "visitorId": "visitor_1761477373779_u4yem2vkm",
    "sessionId": "session_1761477511295_hoc4jd7g9",
    "referrer": "https://momsshift.com/",
    "userAgent": "Mozilla/5.0 (iPhone; CPU iPhone OS 18_6_2 like Mac OS X) AppleWebKit/605.1.15 (KHTML, like Gecko) Version/18.6 Mobile/15E148 Safari/604.1",
    "screenWidth": 390,
    "screenHeight": 844,
    "language": "en-GB",
    "email": "bilkisum@hotmail.com",
    "name": "Bilkisu",
    "country": "United Kingdom"
  },
  {
    "page": "/",
    "timestamp": "2025-10-26T11:55:25.778Z",
    "event": "page_visit",
    "visitorId": "visitor_1761479725778_p25xeql11",
    "sessionId": "session_1761479725778_115qsc4di",
    "referrer": "Direct",
    "userAgent": "Mozilla/5.0 (iPhone; CPU iPhone OS 18_7 like Mac OS X) AppleWebKit/605.1.15 (KHTML, like Gecko) Version/26.0.1 Mobile/15E148 Safari/604.1",
    "screenWidth": 393,
    "screenHeight": 852,
    "language": "en-GB",
    "hookVariant": "B"
  },
  {
    "page": "/",
    "timestamp": "2025-10-26T11:55:59.950Z",
    "event": "button_click",
    "buttonName": "Join The 3-Day Mothers Challenge (FREE)",
    "referrer": "Direct"
  },
  {
    "page": "/",
    "timestamp": "2025-10-26T11:56:24.984Z",
    "event": "button_click",
    "buttonName": "Register now",
    "referrer": "Direct"
  },
  {
    "page": "/index.html",
    "timestamp": "2025-10-26T11:56:26.299Z",
    "event": "registration",
    "email": "zlauratu@yahoo.com",
    "name": "Lauratu Zakari",
    "firstName": "Lauratu",
    "lastName": "Zakari",
    "country": "United Kingdom",
    "city": "Council Bluffs",
    "source": "Registration Form - The Shift Landing Page",
    "clickfunnelsSuccess": true,
    "hookVariant": "B",
    "visitorId": null
  },
  {
    "page": "/upsell.html",
    "timestamp": "2025-10-26T11:56:28.618Z",
    "event": "page_visit",
    "visitorId": "visitor_1761479788617_rduo2ujxu",
    "sessionId": "session_1761479788617_oviffvrbd",
    "referrer": "https://momsshift.com/",
    "userAgent": "Mozilla/5.0 (iPhone; CPU iPhone OS 18_7 like Mac OS X) AppleWebKit/605.1.15 (KHTML, like Gecko) Version/26.0.1 Mobile/15E148 Safari/604.1",
    "screenWidth": 393,
    "screenHeight": 852,
    "language": "en-GB",
    "email": "zlauratu@yahoo.com",
    "name": "Lauratu",
    "country": "United Kingdom"
  },
  {
    "page": "/",
    "timestamp": "2025-10-26T12:19:01.088Z",
    "event": "page_visit",
    "visitorId": "visitor_1761481140934_a8aqj3ghf",
    "sessionId": "session_1761481140935_cwx1x9i4c",
    "referrer": "Direct",
    "userAgent": "Mozilla/5.0 (Windows NT 10.0; Win64; x64) AppleWebKit/537.36 (KHTML, like Gecko) Chrome/141.0.0.0 Safari/537.36",
    "screenWidth": 1920,
    "screenHeight": 1080,
    "language": "en-GB",
    "hookVariant": "B"
  },
  {
    "page": "/",
    "timestamp": "2025-10-26T12:24:07.739Z",
    "event": "page_visit",
    "visitorId": "visitor_1761411933753_g5xzl3915",
    "sessionId": "session_1761481447738_9u9t74fm0",
    "referrer": "Direct",
    "userAgent": "Mozilla/5.0 (Macintosh; Intel Mac OS X 10_15_7) AppleWebKit/537.36 (KHTML, like Gecko) Chrome/141.0.0.0 Safari/537.36",
    "screenWidth": 1920,
    "screenHeight": 1080,
    "language": "en-AU",
    "hookVariant": "A",
    "ipAddress": "49.36.180.216",
    "city": "New Delhi",
    "region": "National Capital Territory of Delhi",
    "timezone": "Asia/Kolkata",
    "country": "India",
    "countryCode": "IN"
  },
  {
    "page": "/",
    "timestamp": "2025-10-26T12:27:56.125Z",
    "event": "page_exit",
    "sessionId": "session_1761481447738_9u9t74fm0",
    "duration": 12
  },
  {
    "page": "/thank-you.html",
    "timestamp": "2025-10-26T12:31:03.227Z",
    "event": "page_visit",
    "visitorId": "visitor_1761470358477_heeskqj8m",
    "sessionId": "session_1761481863225_t33m7npap",
    "referrer": "https://momsshift.com/upsell.html?email=adeebarani%40hotmail.co.uk&name=Adeeba&country=United%20Kingdom&variant=A",
    "userAgent": "Mozilla/5.0 (iPhone; CPU iPhone OS 18_3_2 like Mac OS X) AppleWebKit/605.1.15 (KHTML, like Gecko) Version/18.3.1 Mobile/15E148 Safari/604.1",
    "screenWidth": 390,
    "screenHeight": 844,
    "language": "en-GB"
  },
  {
    "page": "/",
    "timestamp": "2025-10-26T14:10:03.887Z",
    "event": "page_visit",
    "visitorId": "visitor_1761487803882_a6xqtlbqt",
    "sessionId": "session_1761487803882_alkx1a62t",
    "referrer": "Direct",
    "userAgent": "Mozilla/5.0 (X11; Linux x86_64) AppleWebKit/537.36 (KHTML, like Gecko) HeadlessChrome/125.0.6422.60 Safari/537.36",
    "screenWidth": 800,
    "screenHeight": 600,
    "language": "en-US",
    "hookVariant": "A"
  },
  {
    "page": "/",
    "timestamp": "2025-10-26T14:51:16.498Z",
    "event": "page_visit",
    "visitorId": "visitor_1761490276491_uki5ejxee",
    "sessionId": "session_1761490276492_qe4n2tn5g",
    "referrer": "Direct",
    "userAgent": "Mozilla/5.0 (iPhone; CPU iPhone OS 17_6_1 like Mac OS X) AppleWebKit/605.1.15 (KHTML, like Gecko) Version/17.6 Mobile/15E148 Safari/604.1",
    "screenWidth": 375,
    "screenHeight": 812,
    "language": "en-GB",
    "hookVariant": "B",
    "ipAddress": "2600:1900:0:2d02::3200",
    "city": "Council Bluffs",
    "region": "Iowa",
    "timezone": "America/Chicago",
    "country": "United States",
    "countryCode": "US"
  },
  {
    "page": "/",
    "timestamp": "2025-10-26T14:51:25.897Z",
    "event": "button_click",
    "buttonName": "Join The 3-Day Mothers Challenge (FREE)",
    "referrer": "Direct"
  },
  {
    "page": "/index.html",
    "timestamp": "2025-10-26T14:51:49.038Z",
    "event": "registration",
    "email": "khoulashafqat72@gmail.com",
    "name": "Khoula Shafqat",
    "firstName": "Khoula",
    "lastName": "Shafqat",
    "country": "United Kingdom",
    "city": "Council Bluffs",
    "source": "Registration Form - The Shift Landing Page",
    "clickfunnelsSuccess": true,
    "hookVariant": "B",
    "visitorId": null
  },
  {
    "page": "/upsell.html",
    "timestamp": "2025-10-26T14:51:51.523Z",
    "event": "page_visit",
    "visitorId": "visitor_1761490311523_v3lg9o9qf",
    "sessionId": "session_1761490311523_sm57851mh",
    "referrer": "https://momsshift.com/",
    "userAgent": "Mozilla/5.0 (iPhone; CPU iPhone OS 17_6_1 like Mac OS X) AppleWebKit/605.1.15 (KHTML, like Gecko) Version/17.6 Mobile/15E148 Safari/604.1",
    "screenWidth": 375,
    "screenHeight": 812,
    "language": "en-GB",
    "email": "khoulashafqat72@gmail.com",
    "name": "Khoula",
    "ipAddress": "2600:1900:0:2d02::3200",
    "city": "Council Bluffs",
    "region": "Iowa",
    "timezone": "America/Chicago",
    "country": "United Kingdom"
  },
  {
    "page": "/",
    "timestamp": "2025-10-26T14:54:09.798Z",
    "event": "button_click",
    "buttonName": "Join Free Mothers Challenge",
    "referrer": "Direct"
  },
  {
    "page": "/",
    "timestamp": "2025-10-26T16:21:56.991Z",
    "event": "page_visit",
    "visitorId": "visitor_1761495716979_tpr5xvwxx",
    "sessionId": "session_1761495716979_jhrbaoex6",
    "referrer": "Direct",
    "userAgent": "Mozilla/5.0 (iPhone; CPU iPhone OS 10_3_1 like Mac OS X) AppleWebKit/603.1.30 (KHTML, like Gecko) Version/10.0 Mobile/14E304 Safari/602.1",
    "screenWidth": 800,
    "screenHeight": 600,
    "language": "en-US",
    "hookVariant": "B"
  },
  {
    "page": "/upsell.html",
    "timestamp": "2025-10-26T16:29:35.541Z",
    "event": "page_visit",
    "visitorId": "visitor_1761433392495_v1czdaj71",
    "sessionId": "session_1761496175540_utlp0osej",
    "referrer": "https://momsshift.com/",
    "userAgent": "Mozilla/5.0 (iPhone; CPU iPhone OS 18_7 like Mac OS X) AppleWebKit/605.1.15 (KHTML, like Gecko) Version/26.0.1 Mobile/15E148 Safari/604.1",
    "screenWidth": 393,
    "screenHeight": 852,
    "language": "en-US",
    "email": "zawjatfaheem@yahoo.com",
    "name": "Sabah",
    "country": "United States"
  },
  {
    "page": "/",
    "timestamp": "2025-10-26T16:35:33.869Z",
    "event": "page_visit",
    "visitorId": "visitor_1761496533864_ap9uib379",
    "sessionId": "session_1761496533865_6bjtq0p2v",
    "referrer": "Direct",
    "userAgent": "Mozilla/5.0 AppleWebKit/537.36 (KHTML, like Gecko; compatible; bingbot/2.0; +http://www.bing.com/bingbot.htm) Chrome/136.0.0.0 Safari/537.36",
    "screenWidth": 800,
    "screenHeight": 600,
    "language": "en-US",
    "hookVariant": "B"
  },
  {
    "page": "/upsell.html",
    "timestamp": "2025-10-26T17:20:32.530Z",
    "event": "page_visit",
    "visitorId": "visitor_1761479788617_rduo2ujxu",
    "sessionId": "session_1761499232529_6lkd23exa",
    "referrer": "https://momsshift.com/",
    "userAgent": "Mozilla/5.0 (iPhone; CPU iPhone OS 18_7 like Mac OS X) AppleWebKit/605.1.15 (KHTML, like Gecko) Version/26.0.1 Mobile/15E148 Safari/604.1",
    "screenWidth": 393,
    "screenHeight": 852,
    "language": "en-GB",
    "email": "zlauratu@yahoo.com",
    "name": "Lauratu",
    "ipAddress": "2600:1900:0:2d02::3200",
    "city": "Council Bluffs",
    "region": "Iowa",
    "timezone": "America/Chicago",
    "country": "United Kingdom"
  },
  {
    "page": "/",
    "timestamp": "2025-10-26T17:32:04.886Z",
    "event": "page_visit",
    "visitorId": "visitor_1761499924866_ww5bvh3s3",
    "sessionId": "session_1761499924869_4ge4271ms",
    "referrer": "android-app://com.google.android.gm/",
    "userAgent": "Mozilla/5.0 (Linux; Android 10; K) AppleWebKit/537.36 (KHTML, like Gecko) SamsungBrowser/28.0 Chrome/130.0.0.0 Mobile Safari/537.36",
    "screenWidth": 384,
    "screenHeight": 854,
    "language": "en-GB",
    "hookVariant": "B",
    "email": "tanzintanuza@gmail.com"
  },
  {
    "page": "/",
    "timestamp": "2025-10-26T17:32:07.132Z",
    "event": "page_visit",
    "visitorId": "visitor_1761499927132_czzlb28sf",
    "sessionId": "session_1761499927132_5x3bn9rxm",
    "referrer": "Direct",
    "userAgent": "Mozilla/5.0 (Windows NT 10.0; Win64; x64) AppleWebKit/537.36 (KHTML, like Gecko) Chrome/141.0.0.0 Safari/537.36",
    "screenWidth": 1920,
    "screenHeight": 1080,
    "language": "en-GB",
    "hookVariant": "B",
    "email": "tanzintanuza@gmail.com"
  },
  {
    "page": "/",
    "timestamp": "2025-10-26T18:50:32.859Z",
    "event": "page_visit",
    "visitorId": "visitor_1761470661536_s74njzjgn",
    "sessionId": "session_1761504632851_lojbsdnep",
    "referrer": "Direct",
    "userAgent": "Mozilla/5.0 (iPhone; CPU iPhone OS 18_6_2 like Mac OS X) AppleWebKit/605.1.15 (KHTML, like Gecko) CriOS/141.0.7390.96 Mobile/15E148 Safari/604.1",
    "screenWidth": 390,
    "screenHeight": 844,
    "language": "tr-TR",
    "hookVariant": "A",
    "ipAddress": "2600:1900:0:2d02::3200",
    "city": "Council Bluffs",
    "region": "Iowa",
    "timezone": "America/Chicago",
    "country": "United States",
    "countryCode": "US"
  },
  {
    "page": "/",
    "timestamp": "2025-10-26T19:18:13.114Z",
    "event": "page_visit",
    "visitorId": "visitor_1761506293085_3ua2llkz7",
    "sessionId": "session_1761506293086_5pdweoakd",
    "referrer": "Direct",
    "userAgent": "Mozilla/5.0 (X11; Linux x86_64) AppleWebKit/537.36 (KHTML, like Gecko) Chrome/132.0.0.0 Safari/537.3",
    "screenWidth": 800,
    "screenHeight": 600,
    "language": "en-US",
    "hookVariant": "B",
    "ipAddress": "2600:1900:0:2d02::3200",
    "city": "Council Bluffs",
    "region": "Iowa",
    "timezone": "America/Chicago",
    "country": "United States",
    "countryCode": "US"
  },
  {
    "page": "/",
    "timestamp": "2025-10-26T19:20:52.345Z",
    "event": "page_visit",
    "visitorId": "visitor_1761506452338_dx5s8v3gv",
    "sessionId": "session_1761506452339_gfn12d9so",
    "referrer": "android-app://com.google.android.gm/",
    "userAgent": "Mozilla/5.0 (Linux; Android 10; K) AppleWebKit/537.36 (KHTML, like Gecko) Chrome/141.0.0.0 Mobile Safari/537.36",
    "screenWidth": 444,
    "screenHeight": 978,
    "language": "en-AE",
    "hookVariant": "B",
    "email": "mehaboob.unnisa@gmail.com",
    "name": "Mehaboob",
    "ipAddress": "2600:1900:0:2d02::3200",
    "city": "Council Bluffs",
    "region": "Iowa",
    "timezone": "America/Chicago",
    "country": "United States",
    "countryCode": "US"
  },
  {
    "page": "/",
    "timestamp": "2025-10-26T19:21:12.833Z",
    "event": "button_click",
    "buttonName": "Yes, I want to join The Shift Free 3 Day Challenge",
    "referrer": "android-app://com.google.android.gm/"
  },
  {
    "page": "/",
    "timestamp": "2025-10-26T19:21:20.752Z",
    "event": "button_click",
    "buttonName": "Register now",
    "referrer": "android-app://com.google.android.gm/"
  },
  {
    "page": "/index.html",
    "timestamp": "2025-10-26T19:21:22.358Z",
    "event": "registration",
    "email": "mehaboob.unnisa@gmail.com",
    "name": "Mehaboob",
    "firstName": "Mehaboob",
    "lastName": "",
    "country": "United Arab Emirates",
    "city": "Council Bluffs",
    "source": "Registration Form - The Shift Landing Page",
    "clickfunnelsSuccess": true,
    "hookVariant": "B",
    "visitorId": "visitor_1761506452338_dx5s8v3gv"
  },
  {
    "page": "/upsell.html",
    "timestamp": "2025-10-26T19:21:24.945Z",
    "event": "page_visit",
    "visitorId": "visitor_1761506452338_dx5s8v3gv",
    "sessionId": "session_1761506484942_dpli39bph",
    "referrer": "https://momsshift.com/?name=Mehaboob&email=mehaboob.unnisa@gmail.com",
    "userAgent": "Mozilla/5.0 (Linux; Android 10; K) AppleWebKit/537.36 (KHTML, like Gecko) Chrome/141.0.0.0 Mobile Safari/537.36",
    "screenWidth": 444,
    "screenHeight": 978,
    "language": "en-AE",
    "email": "mehaboob.unnisa@gmail.com",
    "name": "Mehaboob",
    "ipAddress": "2600:1900:0:2d02::3200",
    "city": "Council Bluffs",
    "region": "Iowa",
    "timezone": "America/Chicago",
    "country": "United Arab Emirates"
  },
  {
    "page": "/",
    "timestamp": "2025-10-26T19:22:05.094Z",
    "event": "page_visit",
    "visitorId": "visitor_1761506525087_rtiz4o5ov",
    "sessionId": "session_1761506525088_feut6ru87",
    "referrer": "android-app://com.google.android.gm/",
    "userAgent": "Mozilla/5.0 (Linux; Android 10; K) AppleWebKit/537.36 (KHTML, like Gecko) Chrome/141.0.0.0 Mobile Safari/537.36",
    "screenWidth": 412,
    "screenHeight": 915,
    "language": "en-US",
    "hookVariant": "A"
  },
  {
    "page": "/",
    "timestamp": "2025-10-26T19:22:11.678Z",
    "event": "button_click",
    "buttonName": "Join The 3-Day Mothers Challenge (FREE)",
    "referrer": "android-app://com.google.android.gm/"
  },
  {
    "page": "/",
    "timestamp": "2025-10-26T19:22:31.264Z",
    "event": "button_click",
    "buttonName": "Register now",
    "referrer": "android-app://com.google.android.gm/"
  },
  {
    "page": "/index.html",
    "timestamp": "2025-10-26T19:22:32.663Z",
    "event": "registration",
    "email": "sidraasghar11@gmail.com",
    "name": "Sidra Asghar",
    "firstName": "Sidra",
    "lastName": "Asghar",
    "country": "United Kingdom",
    "city": "Council Bluffs",
    "source": "Registration Form - The Shift Landing Page",
    "clickfunnelsSuccess": true,
    "hookVariant": "A",
    "visitorId": "visitor_1761506525087_rtiz4o5ov"
  },
  {
    "page": "/upsell.html",
    "timestamp": "2025-10-26T19:22:35.064Z",
    "event": "page_visit",
    "visitorId": "visitor_1761506525087_rtiz4o5ov",
    "sessionId": "session_1761506555059_v56y2yd62",
    "referrer": "https://momsshift.com/",
    "userAgent": "Mozilla/5.0 (Linux; Android 10; K) AppleWebKit/537.36 (KHTML, like Gecko) Chrome/141.0.0.0 Mobile Safari/537.36",
    "screenWidth": 412,
    "screenHeight": 915,
    "language": "en-US",
    "email": "sidraasghar11@gmail.com",
    "name": "Sidra",
    "ipAddress": "2600:1900:0:2d02::3200",
    "city": "Council Bluffs",
    "region": "Iowa",
    "timezone": "America/Chicago",
    "country": "United Kingdom"
  },
  {
    "page": "/upsell.html",
    "timestamp": "2025-10-26T19:22:37.157Z",
    "event": "page_visit",
    "visitorId": "visitor_1761506557153_ez1qrngps",
    "sessionId": "session_1761506557154_f4s8hztjc",
    "referrer": "Direct",
    "userAgent": "Mozilla/5.0 (Linux; Android 10; K) AppleWebKit/537.36 (KHTML, like Gecko) Chrome/138.0.0.0 Mobile Safari/537.36 (compatible; Google-Read-Aloud; +https://support.google.com/webmasters/answer/1061943)",
    "screenWidth": 400,
    "screenHeight": 400,
    "language": "en-US",
    "email": "sidraasghar11@gmail.com",
    "name": "Sidra",
    "ipAddress": "2600:1900:0:2d02::3200",
    "city": "Council Bluffs",
    "region": "Iowa",
    "timezone": "America/Chicago",
    "country": "United Kingdom"
  },
  {
    "page": "/thank-you.html",
    "timestamp": "2025-10-26T20:40:12.842Z",
    "event": "page_visit",
    "visitorId": "visitor_1761379772018_xthx8mgh3",
    "sessionId": "session_1761511212842_vy90x2moh",
    "referrer": "https://momsshift.com/upsell.html?email=zuleeybal%40gmail.com&name=Zuleekhah&country=United%20Kingdom",
    "userAgent": "Mozilla/5.0 (iPhone; CPU iPhone OS 18_6_2 like Mac OS X) AppleWebKit/605.1.15 (KHTML, like Gecko) CriOS/141.0.7390.96 Mobile/15E148 Safari/604.1",
    "screenWidth": 393,
    "screenHeight": 852,
    "language": "en-GB",
    "ipAddress": "2600:1900:0:2d02::2401",
    "city": "Council Bluffs",
    "region": "Iowa",
    "timezone": "America/Chicago",
    "country": "United States",
    "countryCode": "US"
  },
  {
    "page": "/",
    "timestamp": "2025-10-26T20:43:54.245Z",
    "event": "page_visit",
    "visitorId": "visitor_1761511434241_y26pfhamv",
    "sessionId": "session_1761511434242_tejar8epd",
    "referrer": "Direct",
    "userAgent": "Mozilla/5.0 (Windows NT 10.0; Win64; x64) AppleWebKit/537.36 (KHTML, like Gecko) Chrome/79.0.3945.79 Safari/537.36",
    "screenWidth": 1024,
    "screenHeight": 1024,
    "language": "en-US",
    "hookVariant": "A"
  },
  {
    "page": "/",
    "timestamp": "2025-10-26T20:43:58.951Z",
    "event": "page_visit",
    "visitorId": "visitor_1761511438945_jrvsdljnf",
    "sessionId": "session_1761511438947_t8lqguty6",
    "referrer": "Direct",
    "userAgent": "Mozilla/5.0 (Windows NT 10.0; Win64; x64) AppleWebKit/537.36 (KHTML, like Gecko) Chrome/79.0.3945.79 Safari/537.36",
    "screenWidth": 1024,
    "screenHeight": 1024,
    "language": "en-US",
    "hookVariant": "A"
  },
  {
    "page": "/",
    "timestamp": "2025-10-26T20:49:07.862Z",
    "event": "page_visit",
    "visitorId": "visitor_1761377512928_s98zt9ofi",
    "sessionId": "session_1761511747597_e90k0wq8s",
    "referrer": "Direct",
    "userAgent": "Mozilla/5.0 (Macintosh; Intel Mac OS X 10_15_7) AppleWebKit/537.36 (KHTML, like Gecko) Chrome/141.0.0.0 Safari/537.36",
    "screenWidth": 1920,
    "screenHeight": 1080,
    "language": "en-AU",
    "hookVariant": "A"
  },
  {
    "page": "/",
    "timestamp": "2025-10-26T20:50:29.979Z",
    "event": "page_visit",
    "visitorId": "visitor_1761377512928_s98zt9ofi",
    "sessionId": "session_1761511829977_gpsj4xlkz",
    "referrer": "Direct",
    "userAgent": "Mozilla/5.0 (Macintosh; Intel Mac OS X 10_15_7) AppleWebKit/537.36 (KHTML, like Gecko) Chrome/141.0.0.0 Safari/537.36",
    "screenWidth": 1920,
    "screenHeight": 1080,
    "language": "en-AU",
    "hookVariant": "A",
    "email": "{{contact.email_address}}",
    "name": "{{contact.first_name}}"
  },
  {
    "page": "/",
    "timestamp": "2025-10-26T21:26:08.796Z",
    "event": "page_visit",
    "visitorId": "visitor_1761513968796_sc4qm2cal",
    "sessionId": "session_1761513968796_wbgubmfu7",
    "referrer": "Direct",
    "userAgent": "Mozilla/5.0 (Windows NT 10.0; Win64; x64) AppleWebKit/537.36 (KHTML, like Gecko) Chrome/141.0.0.0 Safari/537.36",
    "screenWidth": 1920,
    "screenHeight": 1080,
    "language": "en-US",
    "hookVariant": "A",
    "ipAddress": "2600:1900:0:2d02::2401",
    "city": "Council Bluffs",
    "region": "Iowa",
    "timezone": "America/Chicago",
    "country": "United States",
    "countryCode": "US"
  },
  {
    "page": "/",
    "timestamp": "2025-10-26T21:30:28.754Z",
    "event": "page_visit",
    "visitorId": "visitor_1761514228693_jlki7afx6",
    "sessionId": "session_1761514228719_uz2d4sbmi",
    "referrer": "Direct",
    "userAgent": "Mozilla/5.0 (Windows NT 10.0; Win64; x64) AppleWebKit/537.36 (KHTML, like Gecko) Chrome/130.0.0.0 Safari/537.36",
    "screenWidth": 1920,
    "screenHeight": 1080,
    "language": "en-US",
    "hookVariant": "A",
    "email": "marwa.hussein@sruc.ac.uk",
    "name": "Marwa"
  },
  {
    "page": "/",
    "timestamp": "2025-10-26T21:31:43.782Z",
    "event": "page_visit",
    "visitorId": "visitor_1761514303777_r0xgarnfs",
    "sessionId": "session_1761514303779_4e6ugfcwg",
    "referrer": "Direct",
    "userAgent": "Mozilla/5.0 (Windows NT 10.0; Win64; x64) AppleWebKit/537.36 (KHTML, like Gecko) Chrome/130.0.0.0 Safari/537.36",
    "screenWidth": 1920,
    "screenHeight": 1080,
    "language": "en-US",
    "hookVariant": "B",
    "email": "dayga.sheriff@scahalifax.com",
    "name": "Dayga"
  },
  {
    "page": "/",
    "timestamp": "2025-10-26T21:35:43.652Z",
    "event": "page_visit",
    "visitorId": "visitor_1761514543648_jdlfshvs6",
    "sessionId": "session_1761514543650_izoh7a9cl",
    "referrer": "Direct",
    "userAgent": "Mozilla/5.0 (Windows NT 10.0; Win64; x64) AppleWebKit/537.36 (KHTML, like Gecko) Chrome/130.0.0.0 Safari/537.36",
    "screenWidth": 1920,
    "screenHeight": 1080,
    "language": "en-US",
    "hookVariant": "A",
    "email": "tahmina.begum@uq.edu.au",
    "name": "Tahmina"
  },
  {
    "page": "/",
    "timestamp": "2025-10-26T21:38:31.365Z",
    "event": "page_visit",
    "visitorId": "visitor_1761514711357_vmet4gqwf",
    "sessionId": "session_1761514711360_d7mfb7ysf",
    "referrer": "Direct",
    "userAgent": "Mozilla/5.0 (Windows NT 10.0; Win64; x64) AppleWebKit/537.36 (KHTML, like Gecko) Chrome/130.0.0.0 Safari/537.36",
    "screenWidth": 1920,
    "screenHeight": 1080,
    "language": "en-US",
    "hookVariant": "B",
    "email": "fatmah.alsharif@unh.edu",
    "name": "Fatima"
  },
  {
    "page": "/",
    "timestamp": "2025-10-26T21:38:53.933Z",
    "event": "page_visit",
    "visitorId": "visitor_1761514733835_ahqu9id71",
    "sessionId": "session_1761514733840_sglvf1kro",
    "referrer": "Direct",
    "userAgent": "Mozilla/5.0 (Windows NT 10.0; Win64; x64) AppleWebKit/537.36 (KHTML, like Gecko) Chrome/130.0.0.0 Safari/537.36",
    "screenWidth": 1920,
    "screenHeight": 1080,
    "language": "en-US",
    "hookVariant": "A",
    "email": "lunver@caminowellbeing.ca",
    "name": "Leyla"
  },
  {
    "page": "/",
    "timestamp": "2025-10-26T21:39:49.017Z",
    "event": "page_visit",
    "visitorId": "visitor_1761514789010_ahc2fm64y",
    "sessionId": "session_1761514789012_oibydqubi",
    "referrer": "Direct",
    "userAgent": "Mozilla/5.0 (Windows NT 10.0; Win64; x64) AppleWebKit/537.36 (KHTML, like Gecko) Chrome/130.0.0.0 Safari/537.36",
    "screenWidth": 1920,
    "screenHeight": 1080,
    "language": "en-US",
    "hookVariant": "B",
    "email": "fatmah.alsharif@unh.edu",
    "name": "Fatima"
  },
  {
    "page": "/",
    "timestamp": "2025-10-26T21:39:54.819Z",
    "event": "page_visit",
    "visitorId": "visitor_1761514794814_o9091fx6y",
    "sessionId": "session_1761514794816_3t9wn44ly",
    "referrer": "Direct",
    "userAgent": "Mozilla/5.0 (Windows NT 10.0; Win64; x64) AppleWebKit/537.36 (KHTML, like Gecko) Chrome/130.0.0.0 Safari/537.36",
    "screenWidth": 1920,
    "screenHeight": 1080,
    "language": "en-US",
    "hookVariant": "A",
    "email": "fatmah.alsharif@unh.edu",
    "name": "Fatima"
  },
  {
    "page": "/",
    "timestamp": "2025-10-26T21:44:42.733Z",
    "event": "page_visit",
    "visitorId": "visitor_1761515082725_74l8ewov6",
    "sessionId": "session_1761515082729_nc25qd9lx",
    "referrer": "Direct",
    "userAgent": "Mozilla/5.0 (Windows NT 10.0; Win64; x64) AppleWebKit/537.36 (KHTML, like Gecko) Chrome/130.0.0.0 Safari/537.36",
    "screenWidth": 1920,
    "screenHeight": 1080,
    "language": "en-US",
    "hookVariant": "A",
    "email": "m.imroz@nhs.net",
    "name": "Mahbuba"
  },
  {
    "page": "/",
    "timestamp": "2025-10-26T21:49:06.786Z",
    "event": "page_visit",
    "visitorId": "visitor_1761515346715_se8subty0",
    "sessionId": "session_1761515346721_i8i9w35hg",
    "referrer": "Direct",
    "userAgent": "Mozilla/5.0 (Windows NT 10.0; Win64; x64) AppleWebKit/537.36 (KHTML, like Gecko) Chrome/130.0.0.0 Safari/537.36",
    "screenWidth": 1920,
    "screenHeight": 1080,
    "language": "en-US",
    "hookVariant": "A",
    "email": "quadir@uwindsor.ca",
    "name": "Khadija"
  },
  {
    "page": "/",
    "timestamp": "2025-10-26T21:49:33.464Z",
    "event": "page_visit",
    "visitorId": "visitor_1761515373452_jw9bkejyq",
    "sessionId": "session_1761515373456_1fa8y1i75",
    "referrer": "Direct",
    "userAgent": "Mozilla/5.0 (Windows NT 10.0; Win64; x64) AppleWebKit/537.36 (KHTML, like Gecko) Chrome/130.0.0.0 Safari/537.36",
    "screenWidth": 1920,
    "screenHeight": 1080,
    "language": "en-US",
    "hookVariant": "A",
    "email": "abdussnu@kean.edu",
    "name": "Nuri"
  },
  {
    "page": "/",
    "timestamp": "2025-10-26T21:50:01.084Z",
    "event": "page_visit",
    "visitorId": "visitor_1761515401071_p4hrbc1dd",
    "sessionId": "session_1761515401081_r23v5cx40",
    "referrer": "Direct",
    "userAgent": "Mozilla/5.0 (Windows NT 10.0; Win64; x64) AppleWebKit/537.36 (KHTML, like Gecko) Chrome/130.0.0.0 Safari/537.36",
    "screenWidth": 1920,
    "screenHeight": 1080,
    "language": "en-US",
    "hookVariant": "A",
    "email": "samar.hameed@nhs.net",
    "name": "Samar"
  },
  {
    "page": "/",
    "timestamp": "2025-10-26T21:50:47.727Z",
    "event": "page_visit",
    "visitorId": "visitor_1761515447701_tc126y7pu",
    "sessionId": "session_1761515447701_rtqrxpq2n",
    "referrer": "Direct",
    "userAgent": "Mozilla/5.0 (X11; Linux x86_64) AppleWebKit/537.36 (KHTML, like Gecko) Chrome/124.0.0.0 Safari/537.36",
    "screenWidth": 800,
    "screenHeight": 600,
    "language": "en-US",
    "hookVariant": "A",
    "email": "rehanask@al-madinah.school.nz",
    "name": "Rehana"
  },
  {
    "page": "/",
    "timestamp": "2025-10-26T21:53:09.767Z",
    "event": "page_visit",
    "visitorId": "visitor_1761515589756_jep6569nx",
    "sessionId": "session_1761515589761_83r0zapf6",
    "referrer": "Direct",
    "userAgent": "Mozilla/5.0 (Windows NT 10.0; Win64; x64) AppleWebKit/537.36 (KHTML, like Gecko) Chrome/130.0.0.0 Safari/537.36",
    "screenWidth": 1920,
    "screenHeight": 1080,
    "language": "en-US",
    "hookVariant": "A",
    "email": "rehanask@al-madinah.school.nz",
    "name": "Rehana"
  },
  {
    "page": "/",
    "timestamp": "2025-10-26T21:53:28.409Z",
    "event": "page_visit",
    "visitorId": "visitor_1761515608405_g79iomqjh",
    "sessionId": "session_1761515608405_4px5t9u1k",
    "referrer": "Direct",
    "userAgent": "Mozilla/5.0 (X11; Linux x86_64) AppleWebKit/537.36 (KHTML, like Gecko) Chrome/124.0.0.0 Safari/537.36",
    "screenWidth": 800,
    "screenHeight": 600,
    "language": "en-US",
    "hookVariant": "A",
    "email": "rehanask@al-madinah.school.nz",
    "name": "Rehana"
  },
  {
    "page": "/",
    "timestamp": "2025-10-26T21:53:54.519Z",
    "event": "page_visit",
    "visitorId": "visitor_1761515634403_b5lfw10yv",
    "sessionId": "session_1761515634441_c4c385sdy",
    "referrer": "Direct",
    "userAgent": "Mozilla/5.0 (Windows NT 10.0; Win64; x64) AppleWebKit/537.36 (KHTML, like Gecko) Chrome/139.0.0.0 Safari/537.36",
    "screenWidth": 1536,
    "screenHeight": 864,
    "language": "en-US",
    "hookVariant": "A",
    "email": "rehanask@al-madinah.school.nz",
    "name": "Rehana"
  },
  {
    "page": "/",
    "timestamp": "2025-10-26T21:54:15.415Z",
    "event": "page_visit",
    "visitorId": "visitor_1761515655407_hov602g14",
    "sessionId": "session_1761515655409_6p8600c3u",
    "referrer": "Direct",
    "userAgent": "Mozilla/5.0 (Windows NT 10.0; Win64; x64) AppleWebKit/537.36 (KHTML, like Gecko) Chrome/130.0.0.0 Safari/537.36",
    "screenWidth": 1920,
    "screenHeight": 1080,
    "language": "en-US",
    "hookVariant": "B",
    "email": "rehanask@al-madinah.school.nz",
    "name": "Rehana",
    "ipAddress": "2600:1900:0:2d02::2401",
    "city": "Council Bluffs",
    "region": "Iowa",
    "timezone": "America/Chicago",
    "country": "United States",
    "countryCode": "US"
  },
  {
    "page": "/",
    "timestamp": "2025-10-26T21:59:16.057Z",
    "event": "page_visit",
    "visitorId": "visitor_1761515956053_me18z6cdh",
    "sessionId": "session_1761515956054_7yylye7cw",
    "referrer": "Direct",
    "userAgent": "Mozilla/5.0 (Linux; Android 10; K) AppleWebKit/537.36 (KHTML, like Gecko) Chrome/141.0.0.0 Mobile Safari/537.36 EdgA/141.0.0.0",
    "screenWidth": 360,
    "screenHeight": 780,
    "language": "ar",
    "hookVariant": "B",
    "email": "asma_elmhassani@hotmail.com",
    "name": "Asma"
  },
  {
    "page": "/",
    "timestamp": "2025-10-26T21:59:37.096Z",
    "event": "page_visit",
    "visitorId": "visitor_1761515977066_lcm0ryh7t",
    "sessionId": "session_1761515977081_vfs7pfgbi",
    "referrer": "Direct",
    "userAgent": "Mozilla/5.0 (Windows NT 10.0; Win64; x64) AppleWebKit/537.36 (KHTML, like Gecko) Chrome/130.0.0.0 Safari/537.36",
    "screenWidth": 1920,
    "screenHeight": 1080,
    "language": "en-US",
    "hookVariant": "B",
    "email": "asma_elmhassani@hotmail.com",
    "name": "Asma"
  },
  {
    "page": "/",
    "timestamp": "2025-10-26T22:00:22.060Z",
    "event": "button_click",
    "buttonName": "Join Free Mothers Challenge",
    "referrer": "Direct"
  },
  {
    "page": "/upsell.html",
    "timestamp": "2025-10-26T22:00:39.974Z",
    "event": "page_visit",
    "visitorId": "visitor_1761515956053_me18z6cdh",
    "sessionId": "session_1761516039973_1gjbikbsq",
    "referrer": "https://momsshift.com/?email=asma_elmhassani@hotmail.com&name=Asma",
    "userAgent": "Mozilla/5.0 (Linux; Android 10; K) AppleWebKit/537.36 (KHTML, like Gecko) Chrome/141.0.0.0 Mobile Safari/537.36 EdgA/141.0.0.0",
    "screenWidth": 360,
    "screenHeight": 780,
    "language": "ar",
    "email": "asma_elmhassani@hotmail.com",
    "name": "Asma",
    "ipAddress": "2600:1900:0:2d02::2401",
    "city": "Council Bluffs",
    "region": "Iowa",
    "timezone": "America/Chicago",
    "country": "Netherlands"
  },
  {
    "page": "/",
    "timestamp": "2025-10-26T22:01:44.317Z",
    "event": "page_visit",
    "visitorId": "visitor_1761516104308_gvmrby01t",
    "sessionId": "session_1761516104310_gabg66qrh",
    "referrer": "Direct",
    "userAgent": "Mozilla/5.0 (Windows NT 10.0; Win64; x64) AppleWebKit/537.36 (KHTML, like Gecko) Chrome/130.0.0.0 Safari/537.36",
    "screenWidth": 1920,
    "screenHeight": 1080,
    "language": "en-US",
    "hookVariant": "B",
    "email": "ay_c1068@police.gov.mv",
    "name": "N/A",
    "ipAddress": "2600:1900:0:2d02::2401",
    "city": "Council Bluffs",
    "region": "Iowa",
    "timezone": "America/Chicago",
    "country": "United States",
    "countryCode": "US"
  },
  {
    "page": "/",
    "timestamp": "2025-10-26T22:02:35.498Z",
    "event": "page_visit",
    "visitorId": "visitor_1761515956053_me18z6cdh",
    "sessionId": "session_1761516155497_6899vj9fj",
    "referrer": "Direct",
    "userAgent": "Mozilla/5.0 (Linux; Android 10; K) AppleWebKit/537.36 (KHTML, like Gecko) Chrome/141.0.0.0 Mobile Safari/537.36 EdgA/141.0.0.0",
    "screenWidth": 360,
    "screenHeight": 780,
    "language": "ar",
    "hookVariant": "B",
    "email": "asma_elmhassani@hotmail.com",
    "name": "Asma",
    "ipAddress": "2600:1900:0:2d02::2401",
    "city": "Council Bluffs",
    "region": "Iowa",
    "timezone": "America/Chicago",
    "country": "United States",
    "countryCode": "US"
  },
  {
    "page": "/",
    "timestamp": "2025-10-26T22:03:10.185Z",
    "event": "page_visit",
    "visitorId": "visitor_1761516190175_04z6o5zx7",
    "sessionId": "session_1761516190179_muesrj5tg",
    "referrer": "Direct",
    "userAgent": "Mozilla/5.0 (Windows NT 10.0; Win64; x64) AppleWebKit/537.36 (KHTML, like Gecko) Chrome/130.0.0.0 Safari/537.36",
    "screenWidth": 1920,
    "screenHeight": 1080,
    "language": "en-US",
    "hookVariant": "B",
    "email": "asma_elmhassani@hotmail.com",
    "name": "Asma",
    "ipAddress": "2600:1900:0:2d02::2401",
    "city": "Council Bluffs",
    "region": "Iowa",
    "timezone": "America/Chicago",
    "country": "United States",
    "countryCode": "US"
  },
  {
    "page": "/",
    "timestamp": "2025-10-26T22:05:03.525Z",
    "event": "page_visit",
    "visitorId": "visitor_1761401698231_brswqc1mu",
    "sessionId": "session_1761516303489_7fan88epg",
    "referrer": "https://321db0af-5dc4-4f21-af09-8dd8f11e9339-00-11u5kpjldgot0.sisko.repl.co:3000/__replco/workspace_iframe.html?initialPath=%2F&id=%3Arj7%3A",
    "userAgent": "Mozilla/5.0 (Macintosh; Intel Mac OS X 10_15_7) AppleWebKit/537.36 (KHTML, like Gecko) Chrome/141.0.0.0 Safari/537.36",
    "screenWidth": 1920,
    "screenHeight": 1080,
    "language": "en-AU",
    "hookVariant": "A"
  },
  {
    "page": "/",
    "timestamp": "2025-10-26T22:05:43.283Z",
    "event": "page_visit",
    "visitorId": "visitor_1761377088559_blalcmf9s",
    "sessionId": "session_1761516343240_vwir8ag1c",
    "referrer": "https://321db0af-5dc4-4f21-af09-8dd8f11e9339-00-11u5kpjldgot0.sisko.replit.dev:3000/__replco/workspace_iframe.html?initialPath=%2F&id=%3Arj7%3A",
    "userAgent": "Mozilla/5.0 (Macintosh; Intel Mac OS X 10_15_7) AppleWebKit/537.36 (KHTML, like Gecko) Chrome/141.0.0.0 Safari/537.36",
    "screenWidth": 1920,
    "screenHeight": 1080,
    "language": "en-AU",
    "hookVariant": "A"
  },
  {
    "page": "/",
    "timestamp": "2025-10-26T22:14:18.574Z",
    "event": "page_visit",
    "visitorId": "visitor_1761377512928_s98zt9ofi",
    "sessionId": "session_1761516858573_wqqxwi15m",
    "referrer": "Direct",
    "userAgent": "Mozilla/5.0 (Macintosh; Intel Mac OS X 10_15_7) AppleWebKit/537.36 (KHTML, like Gecko) Chrome/141.0.0.0 Safari/537.36",
    "screenWidth": 1920,
    "screenHeight": 1080,
    "language": "en-AU",
    "hookVariant": "A",
    "ipAddress": "2600:1900:0:2d02::1001",
    "city": "Council Bluffs",
    "region": "Iowa",
    "timezone": "America/Chicago",
    "country": "United States",
    "countryCode": "US"
  },
  {
    "page": "/",
    "timestamp": "2025-10-26T22:14:24.016Z",
    "event": "button_click",
    "buttonName": "Join The 3-Day Mothers Challenge (FREE)",
    "referrer": "Direct"
  },
  {
    "page": "/",
    "timestamp": "2025-10-26T22:14:31.247Z",
    "event": "button_click",
    "buttonName": "Register now",
    "referrer": "Direct"
  },
  {
    "page": "/index.html",
    "timestamp": "2025-10-26T22:14:33.085Z",
    "event": "registration",
    "email": "dwer@gmail.com",
    "name": "Ariba Farheen",
    "firstName": "Ariba",
    "lastName": "Farheen",
    "country": "Australia",
    "city": "",
    "source": "Registration Form - The Shift Landing Page",
    "clickfunnelsSuccess": true,
    "hookVariant": "A",
    "visitorId": "visitor_1761377512928_s98zt9ofi"
  },
  {
    "page": "/thank-you.html",
    "timestamp": "2025-10-26T22:14:36.296Z",
    "event": "page_visit",
    "visitorId": "visitor_1761377512928_s98zt9ofi",
    "sessionId": "session_1761516876296_o7hstfn42",
    "referrer": "https://momsshift.com/",
    "userAgent": "Mozilla/5.0 (Macintosh; Intel Mac OS X 10_15_7) AppleWebKit/537.36 (KHTML, like Gecko) Chrome/141.0.0.0 Safari/537.36",
    "screenWidth": 1920,
    "screenHeight": 1080,
    "language": "en-AU",
    "email": "dwer@gmail.com",
    "name": "Ariba",
    "ipAddress": "2600:1900:0:2d02::1001",
    "city": "Council Bluffs",
    "region": "Iowa",
    "timezone": "America/Chicago",
    "country": "Australia"
  },
  {
    "page": "/",
    "timestamp": "2025-10-26T22:29:45.647Z",
    "event": "page_visit",
    "visitorId": "visitor_1761377088559_blalcmf9s",
    "sessionId": "session_1761517785320_occ3k0fpp",
    "referrer": "https://321db0af-5dc4-4f21-af09-8dd8f11e9339-00-11u5kpjldgot0.sisko.replit.dev:3000/__replco/workspace_iframe.html?initialPath=%2F&id=%3Ar17s%3A",
    "userAgent": "Mozilla/5.0 (Macintosh; Intel Mac OS X 10_15_7) AppleWebKit/537.36 (KHTML, like Gecko) Chrome/141.0.0.0 Safari/537.36",
    "screenWidth": 1920,
    "screenHeight": 1080,
    "language": "en-AU",
    "hookVariant": "A"
  }
]